rhapsody/__init__.py
rhapsody/multimodal.py
rhapsody/util.py
rhapsody-0.1.0.data/scripts/rhapsody
rhapsody-0.1.0.dist-info/LICENSE
rhapsody-0.1.0.dist-info/METADATA
rhapsody-0.1.0.dist-info/WHEEL
rhapsody-0.1.0.dist-info/entry_points.txt
rhapsody-0.1.0.dist-info/top_level.txt
rhapsody-0.1.0.dist-info/RECORD
