Metadata-Version: 2.1
Name: rhapsody
Version: 0.1.0
Summary: Microbe-metabolite interactions through neural networks
Home-page: UNKNOWN
Author: gneiss development team
Author-email: jamietmorton@gmail.com
Maintainer: gneiss development team
Maintainer-email: jamietmorton@gmail.com
License: BSD-3-Clause
Platform: UNKNOWN
Classifier: Development Status :: 2 - Pre-Alpha
Classifier: License :: OSI Approved :: BSD License
Classifier: Topic :: Software Development :: Libraries
Classifier: Topic :: Scientific/Engineering
Classifier: Topic :: Scientific/Engineering :: Bio-Informatics
Classifier: Programming Language :: Python :: 3
Classifier: Programming Language :: Python :: 3 :: Only
Classifier: Operating System :: Unix
Classifier: Operating System :: POSIX
Classifier: Operating System :: MacOS :: MacOS X
Requires-Dist: biom-format
Requires-Dist: numpy (>=1.9.2)
Requires-Dist: pandas (>=0.18.0)
Requires-Dist: scipy (>=0.15.1)
Requires-Dist: nose (>=1.3.7)
Requires-Dist: scikit-bio (>=0.5.1)
